{
  "project_info": {
    "project_number": "769627028067",
    "firebase_url": "https://deja-photo-team-19.firebaseio.com",
    "project_id": "deja-photo-team-19",
    "storage_bucket": "deja-photo-team-19.appspot.com"
  },
  "client": [
    {
      "client_info": {
        "mobilesdk_app_id": "1:769627028067:android:41cabffdd2db9746",
        "android_client_info": {
          "package_name": "com.android.dejaphoto"
        }
      },
      "oauth_client": [
        {
          "client_id": "769627028067-lc48l78hdo5buhkepmg44ebsk6trhktf.apps.googleusercontent.com",
          "client_type": 1,
          "android_info": {
            "package_name": "com.android.dejaphoto",
            "certificate_hash": "98e7d7e20566610495d72ec9b8fad48e2be2a15b"
          }
        },
        {
          "client_id": "769627028067-40nc7cf90r4qg2ctggcijhmjj359ogg1.apps.googleusercontent.com",
          "client_type": 3
        }
      ],
      "api_key": [
        {
          "current_key": "AIzaSyAZNXt7sauk23i30d0d5mcruDUCrR7_PJ8"
        }
      ],
      "services": {
        "analytics_service": {
          "status": 1
        },
        "appinvite_service": {
          "status": 2,
          "other_platform_oauth_client": [
            {
              "client_id": "769627028067-40nc7cf90r4qg2ctggcijhmjj359ogg1.apps.googleusercontent.com",
              "client_type": 3
            }
          ]
        },
        "ads_service": {
          "status": 2
        }
      }
    }
  ],
  "configuration_version": "1"
}